baumregextrie/README.MD
baumregextrie/__init__.py
baumregextrie/requirements.txt
baumregextrie/thirdparty.json
baumregextrie-0.10.dist-info/LICENSE.rst
baumregextrie-0.10.dist-info/METADATA
baumregextrie-0.10.dist-info/WHEEL
baumregextrie-0.10.dist-info/top_level.txt
baumregextrie-0.10.dist-info/RECORD
