Metadata-Version: 2.1
Name: baumregextrie
Version: 0.10
Summary: A Trie data structure for efficient pattern matching using regular expressions - up to 1000 times faster
Home-page: https://github.com/hansalemaos/baumregextrie
Author: Johannes Fischer
Author-email: aulasparticularesdealemaosp@gmail.com
License: MIT
Keywords: trie,regex,faster
Classifier: Development Status :: 4 - Beta
Classifier: Programming Language :: Python :: 3 :: Only
Classifier: Programming Language :: Python :: 3.10
Classifier: Topic :: Software Development :: Libraries :: Python Modules
Classifier: Topic :: Utilities
License-File: LICENSE.rst
Requires-Dist: mymulti-key-dict
Requires-Dist: regex
